DESCRIPTION.rst
MANIFEST.in
setup.cfg
setup.py
test.data
test.py
test1.data
parse_python_indentation/__init__.py
parse_python_indentation/parser.py
parse_python_indentation.egg-info/PKG-INFO
parse_python_indentation.egg-info/SOURCES.txt
parse_python_indentation.egg-info/dependency_links.txt
parse_python_indentation.egg-info/top_level.txt