Metadata-Version: 1.0
Name: parse-python-indentation
Version: 0.0.3
Summary: python method to parse the indention of a python-style indented file.
Home-page: https://github.com/johanneswilm/parse_python_indentation.py
Author: Johannes Wilm
Author-email: mail@johanneswilm.org
License: Apache 2.0, see LICENCE.txt
Keywords: parsing python development
Platform: UNKNOWN
